jupyter_simlin/__init__.py
jupyter_simlin/_version.py
jupyter_simlin/handlers.py
jupyter_simlin/labextension/package.json
jupyter_simlin/labextension/static/141.0fdbe9a1272730b38cee.js
jupyter_simlin/labextension/static/32.a0956a9b27c4acc3a6e1.js
jupyter_simlin/labextension/static/364.63ac2e2e5bf3ce8e0f9e.js
jupyter_simlin/labextension/static/384.6ad3867ade19983b8956.js
jupyter_simlin/labextension/static/51974f5286418426f16b.module.wasm
jupyter_simlin/labextension/static/559.f27401f049ef08a4a01e.js
jupyter_simlin/labextension/static/559.f27401f049ef08a4a01e.js.LICENSE.txt
jupyter_simlin/labextension/static/576.1f08185dc9ae5df82a68.js
jupyter_simlin/labextension/static/590.e8c393b0e7c9f4532c60.js
jupyter_simlin/labextension/static/594.3055850b132dc8314d30.js
jupyter_simlin/labextension/static/5e2cb203159eae09f4fa.module.wasm
jupyter_simlin/labextension/static/702.ed24f2b31d3fe9f254f1.js
jupyter_simlin/labextension/static/848.6f38b04dfd0354f42c6e.js
jupyter_simlin/labextension/static/944.e5aab029ac5ac837f86b.js
jupyter_simlin/labextension/static/efd7676c0310ed353b2a.module.wasm
jupyter_simlin/labextension/static/remoteEntry.bbf4cba670202bbcc347.js
jupyter_simlin/labextension/static/style.js
jupyter_simlin-0.2.1.data/data/etc/jupyter/jupyter_server_config.d/simlin.json
jupyter_simlin-0.2.1.data/data/share/jupyter/labextensions/jupyter-simlin/install.json
jupyter_simlin-0.2.1.data/data/share/jupyter/labextensions/jupyter-simlin/package.json
jupyter_simlin-0.2.1.data/data/share/jupyter/labextensions/jupyter-simlin/static/141.0fdbe9a1272730b38cee.js
jupyter_simlin-0.2.1.data/data/share/jupyter/labextensions/jupyter-simlin/static/32.a0956a9b27c4acc3a6e1.js
jupyter_simlin-0.2.1.data/data/share/jupyter/labextensions/jupyter-simlin/static/364.63ac2e2e5bf3ce8e0f9e.js
jupyter_simlin-0.2.1.data/data/share/jupyter/labextensions/jupyter-simlin/static/384.6ad3867ade19983b8956.js
jupyter_simlin-0.2.1.dist-info/LICENSE
jupyter_simlin-0.2.1.dist-info/METADATA
jupyter_simlin-0.2.1.dist-info/WHEEL
jupyter_simlin-0.2.1.dist-info/top_level.txt
jupyter_simlin-0.2.1.dist-info/RECORD
