Metadata-Version: 2.1
Name: jupyter-simlin
Version: 0.2.1
Summary: visual editor for system dynamics models
Home-page: https://github.com/bpowers/simlin
Author: Bobby Powers <bobbypowers@gmail.com>
License: Apache-2.0
Keywords: Jupyter,JupyterLab,JupyterLab3,System Dynamics,Simlin
Platform: Linux
Platform: Mac OS X
Platform: Windows
Classifier: License :: OSI Approved :: BSD License
Classifier: Programming Language :: Python
Classifier: Programming Language :: Python :: 3
Classifier: Programming Language :: Python :: 3.6
Classifier: Programming Language :: Python :: 3.7
Classifier: Programming Language :: Python :: 3.8
Classifier: Programming Language :: Python :: 3.9
Classifier: Framework :: Jupyter
Requires-Python: >=3.6
Requires-Dist: jupyterlab (~=3.0)
